{
  "name": "MetaAngel DAO",
  "description": "Initial DAO movement to support and acquire NFT works by women, beginning with World of Women and Boss Beauties.",
  "logoUri": "https://jbx.mypinata.cloud/ipfs/QmdZMVTWQ4NJsgVMLbd1nmRu7G2Hb9sYEx6JLj9yL3EPtW",
  "infoUri": "https://www.metaangeldao.com/",
  "twitter": "metaangeldao",
  "discord": "",
  "payButton": "LFG! 🚀",
  "payDisclosure": "DAO to back, boost, and support projects/businesses by women. Let's succeed as a collective! 💖 If you're keen to join our closed discord group, please message us on twitter or instagram after you've sent your ETH support 💖",
  "tokens": [],
  "version": 3
}