{
  "name": "Study DAO",
  "infoUri": "http://studyn.finance/",
  "logoUri": "https://jbx.mypinata.cloud/ipfs/QmZhdbSiByb8qbEoeXN3BciHu5XzjdCWRbNEGMUzSh1Fcy",
  "description": "First platform in the blockchain web 3.0 based study to earn money.\nAfter this, we will launch the largest and most comprehensive platform of blockchain, and believe me, it will be a creation gem.",
  "twitter": "studynofficial",
  "discord": "https://t.me/StudynOfficial",
  "tokens": [],
  "version": 4,
  "payButton": "",
  "payDisclosure": "First platform in the blockchain web 3.0 based study to earn money.\nAfter this, we will launch the largest and most comprehensive platform of blockchain, and believe me, it will be a creation gem."
}