{
  "name": "Unification of Taiwan",
  "infoUri": "",
  "logoUri": "https://jbx.mypinata.cloud/ipfs/QmNQx8bVWtQR7fbvoDsa8fzKaSU7TJpQivbLyi42XoxU59",
  "description": "The Unification of Taiwan DAO is a collective encryption. Since April 1949, the Chinese People's Liberation Army crossed the Yangtze River to defeat the Nanjing Presidential Palace, declaring the collapse of the Kuomintang regime. Taiwan, China is solid! The ancestors of the land bridge moved to Taiwan for 30,000 years, and after 5,000 years, the waterway was isolated, but the blood was connected. Funds are used to resist and destroy Taiwan independence forces. Until the reunification of Taiwan. Target 200eth, the overflowing Ethereum will be airdropped to the holder.",
  "twitter": "",
  "discord": "",
  "tokens": [],
  "version": 4,
  "archived": false,
  "payButton": "",
  "payDisclosure": ""
}