{
  "name": "ABUNDANCE.DAO",
  "infoUri": "https://www.keysofabundance.com/",
  "logoUri": "https://jbx.mypinata.cloud/ipfs/QmYgTg5VHrKQgtWHmWZREmKAnbAtYbe5f2Qc3niLN8rJ78",
  "description": "KEYS OF ABUNDANCE (KOA)\nThe purpose of Keys of Abundance is to pave the way for all to gain abundance in all aspects of life as it's our birthright as magnetic, magical and powerful beings living our human experience, our vision is to spread awareness to impact millions of lives globally to access limitless abundance which is our birthright, our deepest fears is not that we are inadequate beings our deepest fears is that we are powerful beyond measure we are meant to shine our light brightly by being our authentic self to emit high vibrational frequency to attract all our desires by being who we are and who we destined to become, we are always in a constant state of progression and our energy is valuable",
  "twitter": "keysofabundance",
  "discord": "https://discord.gg/hPbDq5Xw",
  "tokens": [],
  "version": 4,
  "payButton": "",
  "payDisclosure": "Use the keys of Abundance to unlock and uncover yourself to access limitless Abundance that’s your birthright through discovering ones life purpose and connection of mind, body and spirit."
}